{
  "title": "Links #1: 2026/05 Part 1",
  "url": "https://www.lesswrong.com/posts/7EBNE2gfxpySXiREs/links-1-2026-05-part-1",
  "source": "LessWrong",
  "discoveredAt": "2026-05-18T07:18:27.073Z",
  "importance": "critical",
  "summary": "Links #1: 2026/05 Part 1",
  "whyItMatters": "Preface ^means articles I read in full, otherwise assume I skimmed it I show my discovery graph in (via …) blocks, those without (via …) usually come from my RSS reader, or the algorithm in the corresponding website This is approximately a 1 in 20 filter of content This is very disorganized, but hopefully still useful. Sometimes quotes are not in quote bloc…",
  "tags": [
    "Agentic AI / workflow"
  ],
  "issue": "2026-05-18"
}
